fawern_nn/__init__.py
fawern_nn/nn.py
fawern_nn-0.1.1.dist-info/licenses/LICENSE
fawern_nn-0.1.1.dist-info/METADATA
fawern_nn-0.1.1.dist-info/WHEEL
fawern_nn-0.1.1.dist-info/top_level.txt
fawern_nn-0.1.1.dist-info/RECORD
