Metadata-Version: 2.4
Name: fawern_nn
Version: 0.1.1
Summary: A simple neural network implementation.
Author: Fawern
Project-URL: Homepage, https://github.com/fawern/fawern_nn
Classifier: Programming Language :: Python :: 3
Classifier: License :: OSI Approved :: MIT License
Classifier: Operating System :: OS Independent
Requires-Python: >=3.7
License-File: LICENSE
Requires-Dist: numpy>=1.19.0
Requires-Dist: matplotlib>=3.3.0
Requires-Dist: scikit-learn>=0.24.0
Dynamic: license-file
